runStata/__init__.py
runStata/module_runStata.py
runStata/runStata.py
runStata-0.1.1.dist-info/METADATA
runStata-0.1.1.dist-info/WHEEL
runStata-0.1.1.dist-info/top_level.txt
runStata-0.1.1.dist-info/RECORD
